gym_sudoku/__init__.py
gym_sudoku/envs/__init__.py
gym_sudoku/envs/sudoku_env.py
gym_sudoku-1.0.4.dist-info/DESCRIPTION.rst
gym_sudoku-1.0.4.dist-info/METADATA
gym_sudoku-1.0.4.dist-info/RECORD
gym_sudoku-1.0.4.dist-info/WHEEL
gym_sudoku-1.0.4.dist-info/metadata.json
gym_sudoku-1.0.4.dist-info/top_level.txt
