Metadata-Version: 2.0
Name: gym-sudoku
Version: 1.0.4
Summary: Sudoku environment for OpenAI gym
Home-page: https://github.com/artonge/sudokuEnv
Author: artonge
Author-email: artonge@chmn.me
License: GNU GENERAL PUBLIC LICENSE
Requires-Dist: gym
